yabd.py
yabd-0.3.0.dist-info/METADATA
yabd-0.3.0.dist-info/WHEEL
yabd-0.3.0.dist-info/entry_points.txt
yabd-0.3.0.dist-info/licenses/LICENSE
yabd-0.3.0.dist-info/RECORD
