Metadata-Version: 2.4
Name: yabd
Version: 0.3.0
Summary: Yet Another Brightness Daemon
Author-email: Tristan Brugère <67050900+tbrugere@users.noreply.github.com>
License-Expression: CECILL-B
License-File: LICENSE
Requires-Python: >=3.10
Requires-Dist: sdbus<0.13,>=0.12.0
